log_reporting/__init__.py
log_reporting/application/__init__.py
log_reporting/application/generate_report.py
log_reporting/application/ports/__init__.py
log_reporting/application/ports/report_parser.py
log_reporting/application/ports/report_views.py
log_reporting/entities/__init__.py
log_reporting/entities/endpoint.py
log_reporting/entities/log_level.py
log_reporting/entities/log_level_counter.py
log_reporting/entities/report.py
log_reporting/infrastructure/__init__.py
log_reporting/infrastructure/file_parsing.py
log_reporting/infrastructure/lang_tools.py
log_reporting/infrastructure/parsed_log_level.py
log_reporting/infrastructure/parsed_report.py
log_reporting/infrastructure/adapters/__init__.py
log_reporting/infrastructure/adapters/report_parser.py
log_reporting/main/__init__.py
log_reporting/main/cli/__init__.py
log_reporting/main/cli/__main__.py
log_reporting/main/cli/cli.py
log_reporting/main/common/__init__.py
log_reporting/main/common/di.py
log_reporting/presentation/__init__.py
log_reporting/presentation/adapters/__init__.py
log_reporting/presentation/adapters/report_views.py
log_reporting/presentation/cli/__init__.py
log_reporting/presentation/cli/cli.py
log_reporting/presentation/cli/report_view.py
log_reporting/presentation/cli/table.py
log_reporting/presentation/common/__init__.py
log_reporting/presentation/common/di.py
log_reporting-0.1.0.dist-info/METADATA
log_reporting-0.1.0.dist-info/WHEEL
log_reporting-0.1.0.dist-info/entry_points.txt
log_reporting-0.1.0.dist-info/licenses/LICENSE
log_reporting-0.1.0.dist-info/RECORD
