Metadata-Version: 2.4
Name: log-reporting
Version: 0.1.0
Summary: Приложение анализа и формирование отчётов логов
Project-URL: Repository, https://github.com/emptybutton/test-workmate
Author-email: Alexander Smolin <88573504+emptybutton@users.noreply.github.com>
License:                                  Apache License
License-File: LICENSE
Requires-Python: ==3.13.*
Provides-Extra: dev
Requires-Dist: mypy[faster-cache]==1.15.0; extra == 'dev'
Requires-Dist: pytest-asyncio==0.25.3; extra == 'dev'
Requires-Dist: pytest-cov==6.0.0; extra == 'dev'
Requires-Dist: pytest==8.3.4; extra == 'dev'
Requires-Dist: ruff==0.9.7; extra == 'dev'
Provides-Extra: prod
